[
  {
    "url": "https://www.nutriclub.co.id",
    "strategy": "mobile",
    "performance": 63,
    "accessibility": 74,
    "best_practices": 88,
    "seo": 100,
    "run_at_utc": "2025-11-01T23:09:32Z"
  },
  {
    "url": "https://www.nutriclub.co.id",
    "strategy": "mobile",
    "performance": 44,
    "accessibility": 74,
    "best_practices": 88,
    "seo": 100,
    "run_at_utc": "2025-11-02T23:09:22Z"
  },
  {
    "url": "https://www.nutriclub.co.id",
    "strategy": "mobile",
    "performance": 43,
    "accessibility": 74,
    "best_practices": 88,
    "seo": 100,
    "run_at_utc": "2025-11-03T23:10:24Z"
  }
]
